simplemodule/__init__.py
simplemodule/add.py
simplemodule/substract.py
simplemodule/extras/__init__.py
simplemodule/extras/divide.py
simplemodule/extras/multiply.py
felixnz2020_first_package_2-0.0.2.dist-info/METADATA
felixnz2020_first_package_2-0.0.2.dist-info/WHEEL
felixnz2020_first_package_2-0.0.2.dist-info/top_level.txt
felixnz2020_first_package_2-0.0.2.dist-info/RECORD
